[{"tweet_date":"2016-09-19T12:00:00Z","hashtags":[],"retweet":false,"text_ko":"\"반정부군을 지지하는 서방 국가는 물론 시리아 정부군을 지지하는 러시아도 쿠르드인이 이슬람 국가 (단체)에 맞서 싸우는 것을 지지하여, 쿠르드족의 독립이 국제적인 지지를 얻고 있다.\"","tweet_urls":"","screen_name":"kagami8125","tweet_emoticons":"","mentions":[],"topic":"World News","tweet_text":"\"반정부군을 지지하는 서방 국가는 물론 시리아 정부군을 지지하는 러시아도 쿠르드인이 이슬람 국가 (단체)에 맞서 싸우는 것을 지지하여, 쿠르드족의 독립이 국제적인 지지를 얻고 있다.\"","tweet_lang":"ko","tweet_loc":"0,0","username":"르포르타"},{"tweet_date":"2016-09-19T12:00:00Z","hashtags":[],"retweet":false,"text_ko":"\"쿠르드족들은 코바니를 사수하고 2015년 6월 코바니 지역과 자지라 칸톤을 연결하고 2015년 12월부터 유프라테스 강을 건너 아프린 칸톤을 향해 진격중이다.\"","tweet_urls":"","screen_name":"kagami8125","tweet_emoticons":"","mentions":[],"topic":"World News","tweet_text":"\"쿠르드족들은 코바니를 사수하고 2015년 6월 코바니 지역과 자지라 칸톤을 연결하고 2015년 12월부터 유프라테스 강을 건너 아프린 칸톤을 향해 진격중이다.\"","tweet_lang":"ko","tweet_loc":"0,0","username":"르포르타"},{"tweet_date":"2016-09-19T12:00:00Z","hashtags":[],"retweet":false,"text_ko":"\"로자바 혁명(Rojava Revolution) 또는 로자바 분쟁(Rojava conflict)은 시리아 내전의 와중에 로자바를 해방시키고 쿠르드인 다수 지역을 연결하는 쿠르드족들의 운동이다.\"","tweet_urls":"","screen_name":"kagami8125","tweet_emoticons":"","mentions":[],"topic":"World News","tweet_text":"\"로자바 혁명(Rojava Revolution) 또는 로자바 분쟁(Rojava conflict)은 시리아 내전의 와중에 로자바를 해방시키고 쿠르드인 다수 지역을 연결하는 쿠르드족들의 운동이다.\"","tweet_lang":"ko","tweet_loc":"0,0","username":"르포르타"},{"tweet_date":"2016-09-19T12:00:00Z","hashtags":[],"retweet":false,"text_ko":"왜 국내 서점에서는 쿠르드족의 무장투쟁에 대한 책은 찾기 힘든 건가. 아니 IS 관련 책들은 수두룩한데 말이지.","tweet_urls":"","screen_name":"kagami8125","tweet_emoticons":"","mentions":[],"topic":"World News","tweet_text":"왜 국내 서점에서는 쿠르드족의 무장투쟁에 대한 책은 찾기 힘든 건가. 아니 IS 관련 책들은 수두룩한데 말이지.","tweet_lang":"ko","tweet_loc":"0,0","username":"르포르타"},{"tweet_date":"2016-09-17T08:00:00Z","hashtags":["독일","베를린","난민","쿠르드","중동","독일의피터펜"],"retweet":false,"text_ko":"의 집시 족       의피터펜","tweet_urls":"https://t.co/DIeUnrp5M2","screen_name":"realtripberlin","tweet_emoticons":"","mentions":[],"topic":"World News","tweet_text":"중동의 집시 쿠르드족 https://t.co/DIeUnrp5M2 #독일 #베를린 #난민 #쿠르드 #중동 #독일의피터펜","tweet_lang":"ko","tweet_loc":"0,0","username":"리얼트립베를린 #리베"},{"tweet_date":"2016-09-15T09:00:00Z","hashtags":["독일","베를린","난민","쿠르드","중동","독일의피터펜"],"retweet":false,"text_ko":"의 집시 족       의피터펜","tweet_urls":"https://t.co/YlECsSTiqi","screen_name":"RealSori2012","tweet_emoticons":"","mentions":[],"topic":"World News","tweet_text":"중동의 집시 쿠르드족 https://t.co/YlECsSTiqi #독일 #베를린 #난민 #쿠르드 #중동 #독일의피터펜","tweet_lang":"ko","tweet_loc":"0,0","username":"정혜인"},{"tweet_date":"2016-09-14T11:00:00Z","hashtags":[],"retweet":false,"text_ko":" 마흐무드다후드. 시리아 쿠르드족 출신","tweet_urls":"","screen_name":"Clover_Dover_","tweet_emoticons":"","mentions":["sonar_kang"],"topic":"World News","tweet_text":"@sonar_kang 마흐무드다후드. 시리아 쿠르드족 출신","tweet_lang":"ko","tweet_loc":"0,0","username":"남궁철수🍻"},{"tweet_date":"2016-09-14T06:00:00Z","hashtags":["독일","베를린","난민","쿠르드","중동","독일의피터펜"],"retweet":false,"text_ko":"의 집시 족 이야기       의피터펜","tweet_urls":"https://t.co/seHYCZ9QSd","screen_name":"peterspens","tweet_emoticons":"","mentions":[],"topic":"World News","tweet_text":"중동의 집시 쿠르드족 이야기 https://t.co/seHYCZ9QSd #독일 #베를린 #난민 #쿠르드 #중동 #독일의피터펜","tweet_lang":"ko","tweet_loc":"0,0","username":"독일의피터펜"},{"tweet_date":"2016-09-14T12:00:00Z","hashtags":["독일","베를린","난민","쿠르드","중동","독일의피터펜"],"retweet":false,"text_ko":"의 집시라 불리는 족       의피터펜","tweet_urls":"https://t.co/YlECsSTiqi","screen_name":"RealSori2012","tweet_emoticons":"","mentions":[],"topic":"World News","tweet_text":"중동의 집시라 불리는 쿠르드족 https://t.co/YlECsSTiqi #독일 #베를린 #난민 #쿠르드 #중동 #독일의피터펜","tweet_lang":"ko","tweet_loc":"0,0","username":"정혜인"},{"tweet_date":"2016-09-13T10:00:00Z","hashtags":["독일","베를린","난민","쿠르드","중동","독일의피터펜"],"retweet":false,"text_ko":"의 집시라 불리는 족       의피터펜","tweet_urls":"https://t.co/seHYCZ9QSd","screen_name":"peterspens","tweet_emoticons":"","mentions":[],"topic":"World News","tweet_text":"중동의 집시라 불리는 쿠르드족 https://t.co/seHYCZ9QSd #독일 #베를린 #난민 #쿠르드 #중동 #독일의피터펜","tweet_lang":"ko","tweet_loc":"0,0","username":"독일의피터펜"},{"tweet_date":"2016-09-13T08:00:00Z","hashtags":["독일","베를린","난민","쿠르드","중동","독일의피터펜"],"retweet":false,"text_ko":"의 집시 족 이야기       의피터펜","tweet_urls":"https://t.co/YlECsSTiqi","screen_name":"RealSori2012","tweet_emoticons":"","mentions":[],"topic":"World News","tweet_text":"중동의 집시 쿠르드족 이야기 https://t.co/YlECsSTiqi #독일 #베를린 #난민 #쿠르드 #중동 #독일의피터펜","tweet_lang":"ko","tweet_loc":"0,0","username":"정혜인"},{"tweet_date":"2016-09-13T08:00:00Z","hashtags":["독일","베를린","난민","쿠르드","중동","독일의피터펜"],"retweet":false,"text_ko":"의 집시 족 이야기       의피터펜","tweet_urls":"https://t.co/DIeUnrp5M2","screen_name":"realtripberlin","tweet_emoticons":"","mentions":[],"topic":"World News","tweet_text":"중동의 집시 쿠르드족 이야기 https://t.co/DIeUnrp5M2 #독일 #베를린 #난민 #쿠르드 #중동 #독일의피터펜","tweet_lang":"ko","tweet_loc":"0,0","username":"리얼트립베를린 #리베"},{"tweet_date":"2016-09-12T05:00:00Z","hashtags":["독일","베를린","난민","쿠르드","중동","독일의피터펜"],"retweet":false,"text_ko":"의 집시 족 이야기       의피터펜","tweet_urls":"https://t.co/seHYCZ9QSd","screen_name":"peterspens","tweet_emoticons":"","mentions":[],"topic":"World News","tweet_text":"중동의 집시 쿠르드족 이야기 https://t.co/seHYCZ9QSd #독일 #베를린 #난민 #쿠르드 #중동 #독일의피터펜","tweet_lang":"ko","tweet_loc":"0,0","username":"독일의피터펜"},{"tweet_date":"2016-09-12T02:00:00Z","hashtags":[],"retweet":false,"text_ko":"헨리 키신저는 이라크의 발칸화를 요구했다. 쿠르드족이 유전을 얻게 된다면 이에 대해 준비되어 있는 유일한 세력은 그들이 될 것이다. \n\n","tweet_urls":"https://t.co/i8e8WPmsBo","screen_name":"shimarisu49","tweet_emoticons":"","mentions":[],"topic":"World News","tweet_text":"헨리 키신저는 이라크의 발칸화를 요구했다. 쿠르드족이 유전을 얻게 된다면 이에 대해 준비되어 있는 유일한 세력은 그들이 될 것이다. \n\nhttps://t.co/i8e8WPmsBo","tweet_lang":"ko","tweet_loc":"0,0","username":"포로리"},{"tweet_date":"2016-09-11T04:00:00Z","hashtags":[],"retweet":true,"text_ko":" <쿠르드의 안젤리나 졸리가 전사하다> 쿠르드족 여인이 ISIS와 전투중 사망했다 기사에 대한 반응이다. 기자의 몽매함이 부끄럽다.죽음에 이르러서도 여인의 이름을 쓰는 정도의 존중도 없었냐는 지적이 쓰다 ://t.co\u2026","tweet_urls":"","screen_name":"suna383","tweet_emoticons":"","mentions":["cafra365"],"topic":"World News","tweet_text":"RT @cafra365: <쿠르드의 안젤리나 졸리가 전사하다> 쿠르드족 여인이 ISIS와 전투중 사망했다 기사에 대한 반응이다. 기자의 몽매함이 부끄럽다.죽음에 이르러서도 여인의 이름을 쓰는 정도의 존중도 없었냐는 지적이 쓰다 https://t.co\u2026","tweet_lang":"ko","tweet_loc":"0,0","username":"함께살자-共生,livetogether"},{"tweet_date":"2016-09-11T04:00:00Z","hashtags":[],"retweet":true,"text_ko":" <쿠르드의 안젤리나 졸리가 전사하다> 쿠르드족 여인이 ISIS와 전투중 사망했다 기사에 대한 반응이다. 기자의 몽매함이 부끄럽다.죽음에 이르러서도 여인의 이름을 쓰는 정도의 존중도 없었냐는 지적이 쓰다 ://t.co\u2026","tweet_urls":"","screen_name":"kscmylife35","tweet_emoticons":"","mentions":["cafra365"],"topic":"World News","tweet_text":"RT @cafra365: <쿠르드의 안젤리나 졸리가 전사하다> 쿠르드족 여인이 ISIS와 전투중 사망했다 기사에 대한 반응이다. 기자의 몽매함이 부끄럽다.죽음에 이르러서도 여인의 이름을 쓰는 정도의 존중도 없었냐는 지적이 쓰다 https://t.co\u2026","tweet_lang":"ko","tweet_loc":"0,0","username":"市民軍(회광반조)"},{"tweet_date":"2016-09-11T04:00:00Z","hashtags":[],"retweet":true,"text_ko":" <쿠르드의 안젤리나 졸리가 전사하다> 쿠르드족 여인이 ISIS와 전투중 사망했다 기사에 대한 반응이다. 기자의 몽매함이 부끄럽다.죽음에 이르러서도 여인의 이름을 쓰는 정도의 존중도 없었냐는 지적이 쓰다 ://t.co\u2026","tweet_urls":"","screen_name":"dongsun217","tweet_emoticons":"","mentions":["cafra365"],"topic":"World News","tweet_text":"RT @cafra365: <쿠르드의 안젤리나 졸리가 전사하다> 쿠르드족 여인이 ISIS와 전투중 사망했다 기사에 대한 반응이다. 기자의 몽매함이 부끄럽다.죽음에 이르러서도 여인의 이름을 쓰는 정도의 존중도 없었냐는 지적이 쓰다 https://t.co\u2026","tweet_lang":"ko","tweet_loc":"0,0","username":"젬ㅁㅏ"},{"tweet_date":"2016-09-11T03:00:00Z","hashtags":[],"retweet":true,"text_ko":" <쿠르드의 안젤리나 졸리가 전사하다> 쿠르드족 여인이 ISIS와 전투중 사망했다 기사에 대한 반응이다. 기자의 몽매함이 부끄럽다.죽음에 이르러서도 여인의 이름을 쓰는 정도의 존중도 없었냐는 지적이 쓰다 ://t.co\u2026","tweet_urls":"","screen_name":"osatsuma","tweet_emoticons":"","mentions":["cafra365"],"topic":"World News","tweet_text":"RT @cafra365: <쿠르드의 안젤리나 졸리가 전사하다> 쿠르드족 여인이 ISIS와 전투중 사망했다 기사에 대한 반응이다. 기자의 몽매함이 부끄럽다.죽음에 이르러서도 여인의 이름을 쓰는 정도의 존중도 없었냐는 지적이 쓰다 https://t.co\u2026","tweet_lang":"ko","tweet_loc":"0,0","username":"이수희"},{"tweet_date":"2016-09-11T03:00:00Z","hashtags":[],"retweet":true,"text_ko":" <쿠르드의 안젤리나 졸리가 전사하다> 쿠르드족 여인이 ISIS와 전투중 사망했다 기사에 대한 반응이다. 기자의 몽매함이 부끄럽다.죽음에 이르러서도 여인의 이름을 쓰는 정도의 존중도 없었냐는 지적이 쓰다 ://t.co\u2026","tweet_urls":"","screen_name":"raonoori","tweet_emoticons":"","mentions":["cafra365"],"topic":"World News","tweet_text":"RT @cafra365: <쿠르드의 안젤리나 졸리가 전사하다> 쿠르드족 여인이 ISIS와 전투중 사망했다 기사에 대한 반응이다. 기자의 몽매함이 부끄럽다.죽음에 이르러서도 여인의 이름을 쓰는 정도의 존중도 없었냐는 지적이 쓰다 https://t.co\u2026","tweet_lang":"ko","tweet_loc":"0,0","username":"나는 DNR"},{"tweet_date":"2016-09-11T03:00:00Z","hashtags":[],"retweet":false,"text_ko":"<쿠르드의 안젤리나 졸리가 전사하다> 쿠르드족 여인이 ISIS와 전투중 사망했다 기사에 대한 반응이다. 기자의 몽매함이 부끄럽다.죽음에 이르러서도 여인의 이름을 쓰는 정도의 존중도 없었냐는 지적이 쓰다 ://t.co/d2pvh6sBGD","tweet_urls":"","screen_name":"cafra365","tweet_emoticons":"","mentions":[],"topic":"World News","tweet_text":"<쿠르드의 안젤리나 졸리가 전사하다> 쿠르드족 여인이 ISIS와 전투중 사망했다 기사에 대한 반응이다. 기자의 몽매함이 부끄럽다.죽음에 이르러서도 여인의 이름을 쓰는 정도의 존중도 없었냐는 지적이 쓰다 https://t.co/d2pvh6sBGD","tweet_lang":"ko","tweet_loc":"0,0","username":"🇨 🇦 🇫 🇷 🇦 ✏"},{"tweet_date":"2016-09-11T09:00:00Z","hashtags":[],"retweet":false,"text_ko":"⊙ 중대형 무인기 관제할 항공법 없어 국내 관련법은 총체적 난국⊙ 국내 무인기 조종 면허도 없고, 조종사 양성기관도 없어⊙ 美 공군,\u201c무인기 조종사 1명 양성하는 데 최소 1년\u201d⊙ 테러집단 IS, 쿠르드족 민병대, 터키 국경수비대 모두 무인기 사용 중","tweet_urls":"","screen_name":"LifeIsLikeJazz","tweet_emoticons":"","mentions":[],"topic":"World News","tweet_text":"⊙ 중대형 무인기 관제할 항공법 없어 국내 관련법은 총체적 난국⊙ 국내 무인기 조종 면허도 없고, 조종사 양성기관도 없어⊙ 美 공군,\u201c무인기 조종사 1명 양성하는 데 최소 1년\u201d⊙ 테러집단 IS, 쿠르드족 민병대, 터키 국경수비대 모두 무인기 사용 중","tweet_lang":"ko","tweet_loc":"0,0","username":"푸른하늘"},{"tweet_date":"2016-09-11T02:00:00Z","hashtags":[],"retweet":false,"text_ko":"\n쿠르드족인걸 부인하며 스스로 지를 터키인이라고 생각함\n성격 겁나 더럽고 입이 험함","tweet_urls":"","screen_name":"XxxBomya","tweet_emoticons":"","mentions":["XxxBomya"],"topic":"World News","tweet_text":"@XxxBomya\n쿠르드족인걸 부인하며 스스로 지를 터키인이라고 생각함\n성격 겁나 더럽고 입이 험함","tweet_lang":"ko","tweet_loc":"0,0","username":"연쇄알티러 보먀"},{"tweet_date":"2016-09-11T02:00:00Z","hashtags":[],"retweet":false,"text_ko":"아이셰는 래퍼 지망하는 시리아 출신의 평범한 쿠르드족 학생. 아마르라인가 뭐시긴가 하는 애랑 친구였지만 터키로 국적 세탁하고 나서 자국의 입장에서 쿠르드족이 테러리스트로 비추어지자 아마르라가 테러리스트라고 생각되어서 배신때리고 욕과 디스폭탄을 날림","tweet_urls":"","screen_name":"XxxBomya","tweet_emoticons":"","mentions":[],"topic":"World News","tweet_text":"아이셰는 래퍼 지망하는 시리아 출신의 평범한 쿠르드족 학생. 아마르라인가 뭐시긴가 하는 애랑 친구였지만 터키로 국적 세탁하고 나서 자국의 입장에서 쿠르드족이 테러리스트로 비추어지자 아마르라가 테러리스트라고 생각되어서 배신때리고 욕과 디스폭탄을 날림","tweet_lang":"ko","tweet_loc":"0,0","username":"연쇄알티러 보먀"},{"tweet_date":"2016-09-11T02:00:00Z","hashtags":[],"retweet":false,"text_ko":"아이셰는 래퍼 지망하는 시리아 출신의 평범한 쿠르드족 학생. 아마르라인가 뭐시긴가 하는 애랑 친구였지만 터키로 국적 세탁하고 나서 자국의 입장에서 쿠르드족이 테러리스트로 비추어지자 아마르라가 테러리스트라고 생각되어서 배신때리고 욕과 디스폭탄을 날림","tweet_urls":"","screen_name":"XxxBomya","tweet_emoticons":"","mentions":[],"topic":"World News","tweet_text":"아이셰는 래퍼 지망하는 시리아 출신의 평범한 쿠르드족 학생. 아마르라인가 뭐시긴가 하는 애랑 친구였지만 터키로 국적 세탁하고 나서 자국의 입장에서 쿠르드족이 테러리스트로 비추어지자 아마르라가 테러리스트라고 생각되어서 배신때리고 욕과 디스폭탄을 날림","tweet_lang":"ko","tweet_loc":"0,0","username":"연쇄알티러 보먀"},{"tweet_date":"2016-09-11T02:00:00Z","hashtags":[],"retweet":false,"text_ko":"아이셰는 래퍼 지망하는 시리아 출신의 평범한 쿠르드족 학생. 아마르라인가 뭐시긴가 하는 애랑 친구였지만 터키로 국적 세탁하고 나서 자국의 입장에서 쿠르드족이 테러리스트로 비추어지자 아마르라가 테러리스트라고 생각되어서 배신때리고 욕과 디스폭탄을 날림","tweet_urls":"","screen_name":"XxxBomya","tweet_emoticons":"","mentions":[],"topic":"World News","tweet_text":"아이셰는 래퍼 지망하는 시리아 출신의 평범한 쿠르드족 학생. 아마르라인가 뭐시긴가 하는 애랑 친구였지만 터키로 국적 세탁하고 나서 자국의 입장에서 쿠르드족이 테러리스트로 비추어지자 아마르라가 테러리스트라고 생각되어서 배신때리고 욕과 디스폭탄을 날림","tweet_lang":"ko","tweet_loc":"0,0","username":"연쇄알티러 보먀"},{"tweet_date":"2016-09-11T02:00:00Z","hashtags":[],"retweet":false,"text_ko":"아이셰는 래퍼 지망하는 시리아 출신의 평범한 쿠르드족 학생. 아마르라인가 뭐시긴가 하는 애랑 친구였지만 터키로 국적 세탁하고 나서 자국의 입장에서 쿠르드족이 테러리스트로 비추어지자 아마르라가 테러리스트라고 생각되어서 배신때리고 욕과 디스폭탄을 날림","tweet_urls":"","screen_name":"XxxBomya","tweet_emoticons":"","mentions":[],"topic":"World News","tweet_text":"아이셰는 래퍼 지망하는 시리아 출신의 평범한 쿠르드족 학생. 아마르라인가 뭐시긴가 하는 애랑 친구였지만 터키로 국적 세탁하고 나서 자국의 입장에서 쿠르드족이 테러리스트로 비추어지자 아마르라가 테러리스트라고 생각되어서 배신때리고 욕과 디스폭탄을 날림","tweet_lang":"ko","tweet_loc":"0,0","username":"연쇄알티러 보먀"},{"tweet_date":"2016-09-11T02:00:00Z","hashtags":[],"retweet":false,"text_ko":"아이셰는 래퍼 지망하는 시리아 출신의 평범한 쿠르드족 학생. 아마르라인가 뭐시긴가 하는 애랑 친구였지만 터키로 국적 세탁하고 나서 자국의 입장에서 쿠르드족이 테러리스트로 비추어지자 아마르라가 테러리스트라고 생각되어서 배신때리고 욕과 디스폭탄을 날림","tweet_urls":"","screen_name":"XxxBomya","tweet_emoticons":"","mentions":[],"topic":"World News","tweet_text":"아이셰는 래퍼 지망하는 시리아 출신의 평범한 쿠르드족 학생. 아마르라인가 뭐시긴가 하는 애랑 친구였지만 터키로 국적 세탁하고 나서 자국의 입장에서 쿠르드족이 테러리스트로 비추어지자 아마르라가 테러리스트라고 생각되어서 배신때리고 욕과 디스폭탄을 날림","tweet_lang":"ko","tweet_loc":"0,0","username":"연쇄알티러 보먀"},{"tweet_date":"2016-09-11T02:00:00Z","hashtags":[],"retweet":false,"text_ko":"아이셰는 래퍼 지망하는 시리아 출신의 평범한 쿠르드족 학생. 아마르라인가 뭐시긴가 하는 애랑 친구였지만 터키로 국적 세탁하고 나서 자국의 입장에서 쿠르드족이 테러리스트로 비추어지자 아마르라가 테러리스트라고 생각되어서 배신때리고 욕과 디스폭탄을 날림","tweet_urls":"","screen_name":"XxxBomya","tweet_emoticons":"","mentions":[],"topic":"World News","tweet_text":"아이셰는 래퍼 지망하는 시리아 출신의 평범한 쿠르드족 학생. 아마르라인가 뭐시긴가 하는 애랑 친구였지만 터키로 국적 세탁하고 나서 자국의 입장에서 쿠르드족이 테러리스트로 비추어지자 아마르라가 테러리스트라고 생각되어서 배신때리고 욕과 디스폭탄을 날림","tweet_lang":"ko","tweet_loc":"0,0","username":"연쇄알티러 보먀"},{"tweet_date":"2016-09-11T02:00:00Z","hashtags":[],"retweet":false,"text_ko":"아이셰는 래퍼 지망하는 시리아 출신의 평범한 쿠르드족 학생. 아마르라인가 뭐시긴가 하는 애랑 친구였지만 터키로 국적 세탁하고 나서 자국의 입장에서 쿠르드족이 테러리스트로 비추어지자 아마르라가 테러리스트라고 생각되어서 배신때리고 욕과 디스폭탄을 날림","tweet_urls":"","screen_name":"XxxBomya","tweet_emoticons":"","mentions":[],"topic":"World News","tweet_text":"아이셰는 래퍼 지망하는 시리아 출신의 평범한 쿠르드족 학생. 아마르라인가 뭐시긴가 하는 애랑 친구였지만 터키로 국적 세탁하고 나서 자국의 입장에서 쿠르드족이 테러리스트로 비추어지자 아마르라가 테러리스트라고 생각되어서 배신때리고 욕과 디스폭탄을 날림","tweet_lang":"ko","tweet_loc":"0,0","username":"연쇄알티러 보먀"},{"tweet_date":"2016-09-11T02:00:00Z","hashtags":[],"retweet":false,"text_ko":"아이셰는 래퍼 지망하는 시리아 출신의 평범한 쿠르드족 학생. 아마르라인가 뭐시긴가 하는 애랑 친구였지만 터키로 국적 세탁하고 나서 자국의 입장에서 쿠르드족이 테러리스트로 비추어지자 아마르라가 테러리스트라고 생각되어서 배신때리고 욕과 디스폭탄을 날림","tweet_urls":"","screen_name":"XxxBomya","tweet_emoticons":"","mentions":[],"topic":"World News","tweet_text":"아이셰는 래퍼 지망하는 시리아 출신의 평범한 쿠르드족 학생. 아마르라인가 뭐시긴가 하는 애랑 친구였지만 터키로 국적 세탁하고 나서 자국의 입장에서 쿠르드족이 테러리스트로 비추어지자 아마르라가 테러리스트라고 생각되어서 배신때리고 욕과 디스폭탄을 날림","tweet_lang":"ko","tweet_loc":"0,0","username":"연쇄알티러 보먀"},{"tweet_date":"2016-09-11T02:00:00Z","hashtags":[],"retweet":false,"text_ko":"아이셰는 래퍼 지망하는 시리아 출신의 평범한 쿠르드족 학생. 아마르라인가 뭐시긴가 하는 애랑 친구였지만 터키로 국적 세탁하고 나서 자국의 입장에서 쿠르드족이 테러리스트로 비추어지자 아마르라가 테러리스트라고 생각되어서 배신때리고 욕과 디스폭탄을 날림","tweet_urls":"","screen_name":"XxxBomya","tweet_emoticons":"","mentions":[],"topic":"World News","tweet_text":"아이셰는 래퍼 지망하는 시리아 출신의 평범한 쿠르드족 학생. 아마르라인가 뭐시긴가 하는 애랑 친구였지만 터키로 국적 세탁하고 나서 자국의 입장에서 쿠르드족이 테러리스트로 비추어지자 아마르라가 테러리스트라고 생각되어서 배신때리고 욕과 디스폭탄을 날림","tweet_lang":"ko","tweet_loc":"0,0","username":"연쇄알티러 보먀"},{"tweet_date":"2016-09-11T02:00:00Z","hashtags":[],"retweet":false,"text_ko":"아이셰는 래퍼 지망하는 시리아 출신의 평범한 쿠르드족 학생. 아마르라인가 뭐시긴가 하는 애랑 친구였지만 터키로 국적 세탁하고 나서 자국의 입장에서 쿠르드족이 테러리스트로 비추어지자 아마르라가 테러리스트라고 생각되어서 배신때리고 욕과 디스폭탄을 날림","tweet_urls":"","screen_name":"XxxBomya","tweet_emoticons":"","mentions":[],"topic":"World News","tweet_text":"아이셰는 래퍼 지망하는 시리아 출신의 평범한 쿠르드족 학생. 아마르라인가 뭐시긴가 하는 애랑 친구였지만 터키로 국적 세탁하고 나서 자국의 입장에서 쿠르드족이 테러리스트로 비추어지자 아마르라가 테러리스트라고 생각되어서 배신때리고 욕과 디스폭탄을 날림","tweet_lang":"ko","tweet_loc":"0,0","username":"연쇄알티러 보먀"},{"tweet_date":"2016-09-11T02:00:00Z","hashtags":[],"retweet":false,"text_ko":"아이셰는 래퍼 지망하는 시리아 출신의 평범한 쿠르드족 학생. 아마르라인가 뭐시긴가 하는 애랑 친구였지만 터키로 국적 세탁하고 나서 자국의 입장에서 쿠르드족이 테러리스트로 비추어지자 아마르라가 테러리스트라고 생각되어서 배신때리고 욕과 디스폭탄을 날림","tweet_urls":"","screen_name":"XxxBomya","tweet_emoticons":"","mentions":[],"topic":"World News","tweet_text":"아이셰는 래퍼 지망하는 시리아 출신의 평범한 쿠르드족 학생. 아마르라인가 뭐시긴가 하는 애랑 친구였지만 터키로 국적 세탁하고 나서 자국의 입장에서 쿠르드족이 테러리스트로 비추어지자 아마르라가 테러리스트라고 생각되어서 배신때리고 욕과 디스폭탄을 날림","tweet_lang":"ko","tweet_loc":"0,0","username":"연쇄알티러 보먀"},{"tweet_date":"2016-09-11T02:00:00Z","hashtags":[],"retweet":false,"text_ko":"아이셰는 래퍼 지망하는 시리아 출신의 평범한 쿠르드족 학생. 아마르라인가 뭐시긴가 하는 애랑 친구였지만 터키로 국적 세탁하고 나서 자국의 입장에서 쿠르드족이 테러리스트로 비추어지자 아마르라가 테러리스트라고 생각되어서 배신때리고 욕과 디스폭탄을 날림","tweet_urls":"","screen_name":"XxxBomya","tweet_emoticons":"","mentions":[],"topic":"World News","tweet_text":"아이셰는 래퍼 지망하는 시리아 출신의 평범한 쿠르드족 학생. 아마르라인가 뭐시긴가 하는 애랑 친구였지만 터키로 국적 세탁하고 나서 자국의 입장에서 쿠르드족이 테러리스트로 비추어지자 아마르라가 테러리스트라고 생각되어서 배신때리고 욕과 디스폭탄을 날림","tweet_lang":"ko","tweet_loc":"0,0","username":"연쇄알티러 보먀"},{"tweet_date":"2016-09-11T02:00:00Z","hashtags":[],"retweet":false,"text_ko":"아이셰는 래퍼 지망하는 시리아 출신의 평범한 쿠르드족 학생. 아마르라인가 뭐시긴가 하는 애랑 친구였지만 터키로 국적 세탁하고 나서 자국의 입장에서 쿠르드족이 테러리스트로 비추어지자 아마르라가 테러리스트라고 생각되어서 배신때리고 욕과 디스폭탄을 날림","tweet_urls":"","screen_name":"XxxBomya","tweet_emoticons":"","mentions":[],"topic":"World News","tweet_text":"아이셰는 래퍼 지망하는 시리아 출신의 평범한 쿠르드족 학생. 아마르라인가 뭐시긴가 하는 애랑 친구였지만 터키로 국적 세탁하고 나서 자국의 입장에서 쿠르드족이 테러리스트로 비추어지자 아마르라가 테러리스트라고 생각되어서 배신때리고 욕과 디스폭탄을 날림","tweet_lang":"ko","tweet_loc":"0,0","username":"연쇄알티러 보먀"},{"tweet_date":"2016-09-11T02:00:00Z","hashtags":[],"retweet":false,"text_ko":"아이셰는 래퍼 지망하는 시리아 출신의 평범한 쿠르드족 학생. 아마르라인가 뭐시긴가 하는 애랑 친구였지만 터키로 국적 세탁하고 나서 자국의 입장에서 쿠르드족이 테러리스트로 비추어지자 아마르라가 테러리스트라고 생각되어서 배신때리고 욕과 디스폭탄을 날림","tweet_urls":"","screen_name":"XxxBomya","tweet_emoticons":"","mentions":[],"topic":"World News","tweet_text":"아이셰는 래퍼 지망하는 시리아 출신의 평범한 쿠르드족 학생. 아마르라인가 뭐시긴가 하는 애랑 친구였지만 터키로 국적 세탁하고 나서 자국의 입장에서 쿠르드족이 테러리스트로 비추어지자 아마르라가 테러리스트라고 생각되어서 배신때리고 욕과 디스폭탄을 날림","tweet_lang":"ko","tweet_loc":"0,0","username":"연쇄알티러 보먀"},{"tweet_date":"2016-09-11T02:00:00Z","hashtags":[],"retweet":false,"text_ko":"아이셰는 래퍼 지망하는 시리아 출신의 평범한 쿠르드족 학생. 아마르라인가 뭐시긴가 하는 애랑 친구였지만 터키로 국적 세탁하고 나서 자국의 입장에서 쿠르드족이 테러리스트로 비추어지자 아마르라가 테러리스트라고 생각되어서 배신때리고 욕과 디스폭탄을 날림","tweet_urls":"","screen_name":"XxxBomya","tweet_emoticons":"","mentions":[],"topic":"World News","tweet_text":"아이셰는 래퍼 지망하는 시리아 출신의 평범한 쿠르드족 학생. 아마르라인가 뭐시긴가 하는 애랑 친구였지만 터키로 국적 세탁하고 나서 자국의 입장에서 쿠르드족이 테러리스트로 비추어지자 아마르라가 테러리스트라고 생각되어서 배신때리고 욕과 디스폭탄을 날림","tweet_lang":"ko","tweet_loc":"0,0","username":"연쇄알티러 보먀"},{"tweet_date":"2016-09-11T02:00:00Z","hashtags":[],"retweet":false,"text_ko":"아이셰는 래퍼 지망하는 시리아 출신의 평범한 쿠르드족 학생. 아마르라인가 뭐시긴가 하는 애랑 친구였지만 터키로 국적 세탁하고 나서 자국의 입장에서 쿠르드족이 테러리스트로 비추어지자 아마르라가 테러리스트라고 생각되어서 배신때리고 욕과 디스폭탄을 날림","tweet_urls":"","screen_name":"XxxBomya","tweet_emoticons":"","mentions":[],"topic":"World News","tweet_text":"아이셰는 래퍼 지망하는 시리아 출신의 평범한 쿠르드족 학생. 아마르라인가 뭐시긴가 하는 애랑 친구였지만 터키로 국적 세탁하고 나서 자국의 입장에서 쿠르드족이 테러리스트로 비추어지자 아마르라가 테러리스트라고 생각되어서 배신때리고 욕과 디스폭탄을 날림","tweet_lang":"ko","tweet_loc":"0,0","username":"연쇄알티러 보먀"},{"tweet_date":"2016-09-11T02:00:00Z","hashtags":[],"retweet":false,"text_ko":"아이셰는 래퍼 지망하는 시리아 출신의 평범한 쿠르드족 학생. 아마르라인가 뭐시긴가 하는 애랑 친구였지만 터키로 국적 세탁하고 나서 자국의 입장에서 쿠르드족이 테러리스트로 비추어지자 아마르라가 테러리스트라고 생각되어서 배신때리고 욕과 디스폭탄을 날림","tweet_urls":"","screen_name":"XxxBomya","tweet_emoticons":"","mentions":[],"topic":"World News","tweet_text":"아이셰는 래퍼 지망하는 시리아 출신의 평범한 쿠르드족 학생. 아마르라인가 뭐시긴가 하는 애랑 친구였지만 터키로 국적 세탁하고 나서 자국의 입장에서 쿠르드족이 테러리스트로 비추어지자 아마르라가 테러리스트라고 생각되어서 배신때리고 욕과 디스폭탄을 날림","tweet_lang":"ko","tweet_loc":"0,0","username":"연쇄알티러 보먀"},{"tweet_date":"2016-09-11T02:00:00Z","hashtags":[],"retweet":false,"text_ko":"아이셰는 래퍼 지망하는 시리아 출신의 평범한 쿠르드족 학생. 아마르라인가 뭐시긴가 하는 애랑 친구였지만 터키로 국적 세탁하고 나서 자국의 입장에서 쿠르드족이 테러리스트로 비추어지자 아마르라가 테러리스트라고 생각되어서 배신때리고 욕과 디스폭탄을 날림","tweet_urls":"","screen_name":"XxxBomya","tweet_emoticons":"","mentions":[],"topic":"World News","tweet_text":"아이셰는 래퍼 지망하는 시리아 출신의 평범한 쿠르드족 학생. 아마르라인가 뭐시긴가 하는 애랑 친구였지만 터키로 국적 세탁하고 나서 자국의 입장에서 쿠르드족이 테러리스트로 비추어지자 아마르라가 테러리스트라고 생각되어서 배신때리고 욕과 디스폭탄을 날림","tweet_lang":"ko","tweet_loc":"0,0","username":"연쇄알티러 보먀"},{"tweet_date":"2016-09-11T02:00:00Z","hashtags":[],"retweet":false,"text_ko":"아이셰는 래퍼 지망하는 시리아 출신의 평범한 쿠르드족 학생. 아마르라인가 뭐시긴가 하는 애랑 친구였지만 터키로 국적 세탁하고 나서 자국의 입장에서 쿠르드족이 테러리스트로 비추어지자 아마르라가 테러리스트라고 생각되어서 배신때리고 욕과 디스폭탄을 날림","tweet_urls":"","screen_name":"XxxBomya","tweet_emoticons":"","mentions":[],"topic":"World News","tweet_text":"아이셰는 래퍼 지망하는 시리아 출신의 평범한 쿠르드족 학생. 아마르라인가 뭐시긴가 하는 애랑 친구였지만 터키로 국적 세탁하고 나서 자국의 입장에서 쿠르드족이 테러리스트로 비추어지자 아마르라가 테러리스트라고 생각되어서 배신때리고 욕과 디스폭탄을 날림","tweet_lang":"ko","tweet_loc":"0,0","username":"연쇄알티러 보먀"},{"tweet_date":"2016-09-11T02:00:00Z","hashtags":[],"retweet":false,"text_ko":"아이셰는 래퍼 지망하는 시리아 출신의 평범한 쿠르드족 학생. 아마르라인가 뭐시긴가 하는 애랑 친구였지만 터키로 국적 세탁하고 나서 자국의 입장에서 쿠르드족이 테러리스트로 비추어지자 아마르라가 테러리스트라고 생각되어서 배신때리고 욕과 디스폭탄을 날림","tweet_urls":"","screen_name":"XxxBomya","tweet_emoticons":"","mentions":[],"topic":"World News","tweet_text":"아이셰는 래퍼 지망하는 시리아 출신의 평범한 쿠르드족 학생. 아마르라인가 뭐시긴가 하는 애랑 친구였지만 터키로 국적 세탁하고 나서 자국의 입장에서 쿠르드족이 테러리스트로 비추어지자 아마르라가 테러리스트라고 생각되어서 배신때리고 욕과 디스폭탄을 날림","tweet_lang":"ko","tweet_loc":"0,0","username":"연쇄알티러 보먀"},{"tweet_date":"2016-09-11T02:00:00Z","hashtags":[],"retweet":false,"text_ko":"아이셰는 래퍼 지망하는 시리아 출신의 평범한 쿠르드족 학생. 아마르라인가 뭐시긴가 하는 애랑 친구였지만 터키로 국적 세탁하고 나서 자국의 입장에서 쿠르드족이 테러리스트로 비추어지자 아마르라가 테러리스트라고 생각되어서 배신때리고 욕과 디스폭탄을 날림","tweet_urls":"","screen_name":"XxxBomya","tweet_emoticons":"","mentions":[],"topic":"World News","tweet_text":"아이셰는 래퍼 지망하는 시리아 출신의 평범한 쿠르드족 학생. 아마르라인가 뭐시긴가 하는 애랑 친구였지만 터키로 국적 세탁하고 나서 자국의 입장에서 쿠르드족이 테러리스트로 비추어지자 아마르라가 테러리스트라고 생각되어서 배신때리고 욕과 디스폭탄을 날림","tweet_lang":"ko","tweet_loc":"0,0","username":"연쇄알티러 보먀"},{"tweet_date":"2016-09-11T02:00:00Z","hashtags":[],"retweet":false,"text_ko":"아이셰는 래퍼 지망하는 시리아 출신의 평범한 쿠르드족 학생. 아마르라인가 뭐시긴가 하는 애랑 친구였지만 터키로 국적 세탁하고 나서 자국의 입장에서 쿠르드족이 테러리스트로 비추어지자 아마르라가 테러리스트라고 생각되어서 배신때리고 욕과 디스폭탄을 날림","tweet_urls":"","screen_name":"XxxBomya","tweet_emoticons":"","mentions":[],"topic":"World News","tweet_text":"아이셰는 래퍼 지망하는 시리아 출신의 평범한 쿠르드족 학생. 아마르라인가 뭐시긴가 하는 애랑 친구였지만 터키로 국적 세탁하고 나서 자국의 입장에서 쿠르드족이 테러리스트로 비추어지자 아마르라가 테러리스트라고 생각되어서 배신때리고 욕과 디스폭탄을 날림","tweet_lang":"ko","tweet_loc":"0,0","username":"연쇄알티러 보먀"},{"tweet_date":"2016-09-11T02:00:00Z","hashtags":[],"retweet":false,"text_ko":"아이셰는 래퍼 지망하는 시리아 출신의 평범한 쿠르드족 학생. 아마르라인가 뭐시긴가 하는 애랑 친구였지만 터키로 국적 세탁하고 나서 자국의 입장에서 쿠르드족이 테러리스트로 비추어지자 아마르라가 테러리스트라고 생각되어서 배신때리고 욕과 디스폭탄을 날림","tweet_urls":"","screen_name":"XxxBomya","tweet_emoticons":"","mentions":[],"topic":"World News","tweet_text":"아이셰는 래퍼 지망하는 시리아 출신의 평범한 쿠르드족 학생. 아마르라인가 뭐시긴가 하는 애랑 친구였지만 터키로 국적 세탁하고 나서 자국의 입장에서 쿠르드족이 테러리스트로 비추어지자 아마르라가 테러리스트라고 생각되어서 배신때리고 욕과 디스폭탄을 날림","tweet_lang":"ko","tweet_loc":"0,0","username":"연쇄알티러 보먀"},{"tweet_date":"2016-09-11T02:00:00Z","hashtags":[],"retweet":false,"text_ko":"아이셰는 래퍼 지망하는 시리아 출신의 평범한 쿠르드족 학생. 아마르라인가 뭐시긴가 하는 애랑 친구였지만 터키로 국적 세탁하고 나서 자국의 입장에서 쿠르드족이 테러리스트로 비추어지자 아마르라가 테러리스트라고 생각되어서 배신때리고 욕과 디스폭탄을 날림","tweet_urls":"","screen_name":"XxxBomya","tweet_emoticons":"","mentions":[],"topic":"World News","tweet_text":"아이셰는 래퍼 지망하는 시리아 출신의 평범한 쿠르드족 학생. 아마르라인가 뭐시긴가 하는 애랑 친구였지만 터키로 국적 세탁하고 나서 자국의 입장에서 쿠르드족이 테러리스트로 비추어지자 아마르라가 테러리스트라고 생각되어서 배신때리고 욕과 디스폭탄을 날림","tweet_lang":"ko","tweet_loc":"0,0","username":"연쇄알티러 보먀"},{"tweet_date":"2016-09-11T02:00:00Z","hashtags":[],"retweet":false,"text_ko":"아이셰는 래퍼 지망하는 시리아 출신의 평범한 쿠르드족 학생. 아마르라인가 뭐시긴가 하는 애랑 친구였지만 터키로 국적 세탁하고 나서 자국의 입장에서 쿠르드족이 테러리스트로 비추어지자 아마르라가 테러리스트라고 생각되어서 배신때리고 욕과 디스폭탄을 날림","tweet_urls":"","screen_name":"XxxBomya","tweet_emoticons":"","mentions":[],"topic":"World News","tweet_text":"아이셰는 래퍼 지망하는 시리아 출신의 평범한 쿠르드족 학생. 아마르라인가 뭐시긴가 하는 애랑 친구였지만 터키로 국적 세탁하고 나서 자국의 입장에서 쿠르드족이 테러리스트로 비추어지자 아마르라가 테러리스트라고 생각되어서 배신때리고 욕과 디스폭탄을 날림","tweet_lang":"ko","tweet_loc":"0,0","username":"연쇄알티러 보먀"}]